osmapy/__init__.py
osmapy/config.txt
osmapy/main.py
osmapy/Changeset/Changeset.py
osmapy/Changeset/ChangesetForm.py
osmapy/Changeset/__init__.py
osmapy/ElementsLoader/ElementsLoader.py
osmapy/ElementsLoader/Node.py
osmapy/ElementsLoader/__init__.py
osmapy/GPXLoader/GPXLoader.py
osmapy/GPXLoader/__init__.py
osmapy/TileLoader/Tile.py
osmapy/TileLoader/TileLoader.py
osmapy/TileLoader/__init__.py
osmapy/Viewer/ElementViewer.py
osmapy/Viewer/LayerManager.py
osmapy/Viewer/OSMCopyright.py
osmapy/Viewer/Viewer.py
osmapy/Viewer/__init__.py
osmapy/assets/appicon.png
osmapy/assets/error.png
osmapy/utils/Point.py
osmapy/utils/__init__.py
osmapy/utils/calc.py
osmapy/utils/config.py
osmapy/utils/config_schema.py
osmapy-0.0.1.8.dist-info/LICENSE
osmapy-0.0.1.8.dist-info/METADATA
osmapy-0.0.1.8.dist-info/WHEEL
osmapy-0.0.1.8.dist-info/entry_points.txt
osmapy-0.0.1.8.dist-info/top_level.txt
osmapy-0.0.1.8.dist-info/RECORD
